lanalyzer/__init__.py
lanalyzer/__main__.py
lanalyzer/__version__.py
lanalyzer/main.py
lanalyzer/analysis/__init__.py
lanalyzer/analysis/base.py
lanalyzer/analysis/import_tracker.py
lanalyzer/analysis/source_sink_classifier.py
lanalyzer/analysis/core/__init__.py
lanalyzer/analysis/core/ast_processor.py
lanalyzer/analysis/core/tracker.py
lanalyzer/analysis/core/visitor.py
lanalyzer/analysis/flow/__init__.py
lanalyzer/analysis/flow/analyzer.py
lanalyzer/analysis/flow/builder.py
lanalyzer/analysis/flow/call_chain_tracker.py
lanalyzer/analysis/models/__init__.py
lanalyzer/analysis/models/constraint_solver.py
lanalyzer/analysis/models/graph.py
lanalyzer/analysis/models/path.py
lanalyzer/analysis/utils/__init__.py
lanalyzer/analysis/utils/formatters.py
lanalyzer/analysis/utils/helpers.py
lanalyzer/cli/__init__.py
lanalyzer/cli/analysis_utils.py
lanalyzer/cli/config_utils.py
lanalyzer/cli/enhanced.py
lanalyzer/cli/file_utils.py
lanalyzer/config/__init__.py
lanalyzer/config/loader.py
lanalyzer/config/settings.py
lanalyzer/logger/__init__.py
lanalyzer/logger/config.py
lanalyzer/logger/core.py
lanalyzer/logger/decorators.py
lanalyzer/mcp/__init__.py
lanalyzer/mcp/__main__.py
lanalyzer/mcp/exceptions.py
lanalyzer/mcp/settings.py
lanalyzer/mcp/cli/__init__.py
lanalyzer/mcp/cli/commands.py
lanalyzer/mcp/handlers/__init__.py
lanalyzer/mcp/handlers/analysis.py
lanalyzer/mcp/handlers/base.py
lanalyzer/mcp/handlers/config.py
lanalyzer/mcp/handlers/explanation.py
lanalyzer/mcp/handlers/registry.py
lanalyzer/mcp/handlers/vulnerability_report.py
lanalyzer/mcp/models/__init__.py
lanalyzer/mcp/models/requests.py
lanalyzer/mcp/models/responses.py
lanalyzer/mcp/models/vulnerability_report.py
lanalyzer/mcp/server/__init__.py
lanalyzer/mcp/server/mcpserver.py
lanalyzer/mcp/templates/__init__.py
lanalyzer/mcp/templates/base_template.py
lanalyzer/mcp/templates/cnvd_template.py
lanalyzer/mcp/templates/cve_template.py
lanalyzer/mcp/tools/__init__.py
lanalyzer/mcp/tools/api.py
lanalyzer-0.2.0.dist-info/METADATA
lanalyzer-0.2.0.dist-info/WHEEL
lanalyzer-0.2.0.dist-info/entry_points.txt
lanalyzer-0.2.0.dist-info/licenses/LICENSE
lanalyzer-0.2.0.dist-info/RECORD
