Metadata-Version: 2.4
Name: lanalyzer
Version: 0.2.0
Summary: Python Taint Analysis Tool for finding security vulnerabilities
Project-URL: Repository, https://github.com/bayuncao/lanalyzer
Author-email: Lanalyzer Author <8533596@gmail.com>
License-Expression: AGPL-3.0-only
License-File: LICENSE
Keywords: mcp,model-context-protocol,security,static-analysis,taint-analysis,vulnerability-detection
Classifier: Development Status :: 3 - Alpha
Classifier: Intended Audience :: Developers
Classifier: License :: OSI Approved :: GNU Affero General Public License v3 or later (AGPLv3+)
Classifier: Programming Language :: Python :: 3
Classifier: Programming Language :: Python :: 3.10
Classifier: Topic :: Security
Classifier: Topic :: Software Development :: Quality Assurance
Requires-Python: <3.11,>=3.10
Requires-Dist: astroid<4,>=3.0.2
Requires-Dist: click<9,>=8.1.7
Requires-Dist: colorama<0.5,>=0.4.6
Requires-Dist: jinja2<4,>=3.1.3
Requires-Dist: psutil<6,>=5.9.0
Requires-Dist: pyyaml<7,>=6.0.1
Requires-Dist: requests<3,>=2.32.3
Requires-Dist: rich<14,>=13.7.0
Provides-Extra: dev
Requires-Dist: black<25.0.0,>=23.7.0; extra == 'dev'
Requires-Dist: build>=1.0.0; extra == 'dev'
Requires-Dist: flake8<7.0.0,>=6.1.0; extra == 'dev'
Requires-Dist: httpx<1.0.0,>=0.24.0; extra == 'dev'
Requires-Dist: isort<6.0.0,>=5.12.0; extra == 'dev'
Requires-Dist: mypy<2.0.0,>=1.5.1; extra == 'dev'
Requires-Dist: pre-commit>=4.2.0; extra == 'dev'
Requires-Dist: pytest-asyncio<1.0.0,>=0.21.0; extra == 'dev'
Requires-Dist: pytest-cov<6.0.0,>=4.1.0; extra == 'dev'
Requires-Dist: pytest<9.0.0,>=7.4.0; extra == 'dev'
Requires-Dist: twine>=4.0.0; extra == 'dev'
Provides-Extra: mcp
Requires-Dist: fastapi<0.115.0,>=0.103.0; extra == 'mcp'
Requires-Dist: fastmcp<3.0.0,>=2.0.0; extra == 'mcp'
Requires-Dist: pydantic<3.0.0,>=2.4.0; extra == 'mcp'
Requires-Dist: uvicorn[standard]<0.30.0,>=0.23.2; extra == 'mcp'
